hsioe
tests
