Metadata-Version: 2.1
Name: HsioeFlask
Version: 0.0.6
Summary: A Simple Flask Business Api Frame!
Home-page: UNKNOWN
Author: hsioe
Author-email: hsioe_david@aliyun.com
License: UNKNOWN
Keywords: Flask,Hsioe,Web
Platform: UNKNOWN
Classifier: Programming Language :: Python :: 3.6
Classifier: License :: OSI Approved :: MIT License
Classifier: Operating System :: OS Independent
